bibliotheca/__init__.py
bibliotheca/githf.py
bibliotheca/machina.yaml
bibliotheca-0.0.1.dist-info/LICENSE
bibliotheca-0.0.1.dist-info/METADATA
bibliotheca-0.0.1.dist-info/WHEEL
bibliotheca-0.0.1.dist-info/top_level.txt
bibliotheca-0.0.1.dist-info/RECORD
